ucp/__init__.py
ucp/ucp_client.py
ucp/ucp_config.py
ucp/ucp_handler.py
ucp/ucp_server.py
ucp/ucp_session.py
ucp/utils.py
ucp_framework-0.0.1.dist-info/METADATA
ucp_framework-0.0.1.dist-info/WHEEL
ucp_framework-0.0.1.dist-info/top_level.txt
ucp_framework-0.0.1.dist-info/RECORD
