Metadata-Version: 2.2
Name: ucp-framework
Version: 0.0.1
Summary: The universal communication protocol combines the benefits of mqtt, with a bi-directional communication framework like WebSockets
Home-page: https://github.com/user2745/ucp
Author: Kevin Kamto
Author-email: Kevin Kamto <kamtokevin@gmail.com>
Project-URL: Homepage, https://github.com/user2745/ucp/README.md
Project-URL: Issues, https://github.com/user2745/ucp/issues
Classifier: Programming Language :: Python :: 3
Classifier: Operating System :: OS Independent
Requires-Python: >=3.8
Dynamic: author
Dynamic: home-page
